[{"lontitude": "120.163973  ", "latitude": "30.278808 " },
{"lontitude": "120.165544  ", "latitude": "30.279700 " },
{"lontitude": "120.167400  ", "latitude": "30.280628 " },
{"lontitude": "120.169434  ", "latitude": "30.281021 " },
{"lontitude": "120.169577  ", "latitude": "30.281057 " },
{"lontitude": "120.171254  ", "latitude": "30.280949 " },
{"lontitude": "120.172254  ", "latitude": "30.280842 " },
{"lontitude": "120.173075  ", "latitude": "30.280914 " },
{"lontitude": "120.172325  ", "latitude": "30.284733 " },
{"lontitude": "120.179606  ", "latitude": "30.285625 " },
{"lontitude": "120.179678  ", "latitude": "30.287231 " },
{"lontitude": "120.179820  ", "latitude": "30.288195 " },
{"lontitude": "120.181855  ", "latitude": "30.288159 " },
{"lontitude": "120.182247  ", "latitude": "30.291157 " },
{"lontitude": "120.183711  ", "latitude": "30.290907 " },
{"lontitude": "120.185174  ", "latitude": "30.290979 " },
{"lontitude": "120.186388  ", "latitude": "30.291229 " },
{"lontitude": "120.186745  ", "latitude": "30.290765 " },
{"lontitude": "120.187101  ", "latitude": "30.289408 " },
{"lontitude": "120.188922  ", "latitude": "30.288516 " },
{"lontitude": "120.186780  ", "latitude": "30.285304 " },
{"lontitude": "120.186316  ", "latitude": "30.280842 " },
{"lontitude": "120.186138  ", "latitude": "30.278165 " },
{"lontitude": "120.195311  ", "latitude": "30.278951 " },
{"lontitude": "120.202770  ", "latitude": "30.279665 " },
{"lontitude": "120.203270  ", "latitude": "30.266066 " },
{"lontitude": "120.203555  ", "latitude": "30.263496 " },
{"lontitude": "120.199629  ", "latitude": "30.263103 " },
{"lontitude": "120.199487  ", "latitude": "30.266030 " },
{"lontitude": "120.190849  ", "latitude": "30.265995 " },
{"lontitude": "120.190921  ", "latitude": "30.257036 " },
{"lontitude": "120.191170  ", "latitude": "30.254466 " },
{"lontitude": "120.185246  ", "latitude": "30.254181 " },
{"lontitude": "120.185246  ", "latitude": "30.255929 " },
{"lontitude": "120.185424  ", "latitude": "30.257143 " },
{"lontitude": "120.185745  ", "latitude": "30.258142 " },
{"lontitude": "120.185210  ", "latitude": "30.260034 " },
{"lontitude": "120.182747  ", "latitude": "30.260355 " },
{"lontitude": "120.182747  ", "latitude": "30.258428 " },
{"lontitude": "120.178286  ", "latitude": "30.258499 " },
{"lontitude": "120.178250  ", "latitude": "30.257214 " },
{"lontitude": "120.177929  ", "latitude": "30.255608 " },
{"lontitude": "120.176037  ", "latitude": "30.255858 " },
{"lontitude": "120.175466  ", "latitude": "30.252646 " },
{"lontitude": "120.173467  ", "latitude": "30.252896 " },
{"lontitude": "120.169755  ", "latitude": "30.253110 " },
{"lontitude": "120.167257  ", "latitude": "30.253110 " },
{"lontitude": "120.167043  ", "latitude": "30.255073 " },
{"lontitude": "120.167078  ", "latitude": "30.260462 " },
{"lontitude": "120.176144  ", "latitude": "30.260427 " },
{"lontitude": "120.176144  ", "latitude": "30.266887 " },
{"lontitude": "120.176144  ", "latitude": "30.269171 " },
{"lontitude": "120.175573  ", "latitude": "30.272526 " },
{"lontitude": "120.178393  ", "latitude": "30.272705 " },
{"lontitude": "120.175573  ", "latitude": "30.272526 " },
{"lontitude": "120.174934  ", "latitude": "30.275419 " },
{"lontitude": "120.174458  ", "latitude": "30.277114 " },
{"lontitude": "120.166011  ", "latitude": "30.276460 " },
{"lontitude": "120.165476  ", "latitude": "30.279672 " },
{"lontitude": "120.164018  ", "latitude": "30.278839 " }]